mkdocstrings_handlers/crystal/__init__.py
mkdocstrings_handlers/crystal/collector.py
mkdocstrings_handlers/crystal/crystal_html.py
mkdocstrings_handlers/crystal/deduplicate_toc.py
mkdocstrings_handlers/crystal/inventory.py
mkdocstrings_handlers/crystal/items.py
mkdocstrings_handlers/crystal/macros.py
mkdocstrings_handlers/crystal/py.typed
mkdocstrings_handlers/crystal/renderer.py
mkdocstrings_handlers/crystal/templates/material/constant.html
mkdocstrings_handlers/crystal/templates/material/method.html
mkdocstrings_handlers/crystal/templates/material/style.css
mkdocstrings_handlers/crystal/templates/material/type.html
mkdocstrings_crystal-0.3.9.dist-info/METADATA
mkdocstrings_crystal-0.3.9.dist-info/WHEEL
mkdocstrings_crystal-0.3.9.dist-info/entry_points.txt
mkdocstrings_crystal-0.3.9.dist-info/licenses/LICENSE.md
mkdocstrings_crystal-0.3.9.dist-info/RECORD
