Metadata-Version: 2.4
Name: mkdocstrings-crystal
Version: 0.3.9
Summary: Crystal language doc generator for MkDocs, via mkdocstrings
Project-URL: Documentation, https://mkdocstrings.github.io/crystal/
Project-URL: Source, https://github.com/mkdocstrings/crystal
Project-URL: Issues, https://github.com/mkdocstrings/crystal/issues
Project-URL: History, https://github.com/mkdocstrings/crystal/releases
Author-email: Oleh Prypin <oleh@pryp.in>
License-Expression: MIT
License-File: LICENSE.md
Keywords: crystal,mkdocs,mkdocs-plugin,mkdocstrings
Classifier: Development Status :: 4 - Beta
Classifier: Environment :: Console
Classifier: Environment :: Web Environment
Classifier: Intended Audience :: Developers
Classifier: License :: OSI Approved :: MIT License
Classifier: Operating System :: OS Independent
Classifier: Programming Language :: Python
Classifier: Programming Language :: Python :: 3.9
Classifier: Programming Language :: Python :: 3.10
Classifier: Programming Language :: Python :: 3.11
Classifier: Programming Language :: Python :: 3.12
Classifier: Programming Language :: Python :: 3.13
Classifier: Topic :: Documentation
Classifier: Topic :: Software Development :: Documentation
Classifier: Topic :: Text Processing :: Markup :: Markdown
Classifier: Typing :: Typed
Requires-Python: >=3.9
Requires-Dist: jinja2>=2.11.2
Requires-Dist: markdown-callouts>=0.1.0
Requires-Dist: markupsafe>=1.1.1
Requires-Dist: mkdocs-autorefs>=0.3.1
Requires-Dist: mkdocstrings>=0.30.0
